FeatherMem/__init__.py
feathermem-0.0.1.dist-info/METADATA
feathermem-0.0.1.dist-info/WHEEL
feathermem-0.0.1.dist-info/top_level.txt
feathermem-0.0.1.dist-info/RECORD
