Metadata-Version: 2.4
Name: feathermem
Version: 0.0.1
Summary: Feather Memory.
Requires-Python: >=3.8
